appdynamics/__init__.py
appdynamics/config/__init__.py
appdynamics/config/agent_config.py
appdynamics/config/agent_config_response.py
appdynamics/core/__init__.py
appdynamics/core/profiler.py
appdynamics/core/tracer.py
appdynamics/correlation/__init__.py
appdynamics/correlation/correlation_header.py
appdynamics/eum/__init__.py
appdynamics/eum/eum.py
appdynamics/eum/eum_cookie.py
appdynamics/events/__init__.py
appdynamics/events/backend_registration_event.py
appdynamics/events/bt_event.py
appdynamics/events/bt_registration_event.py
appdynamics/events/error_event.py
appdynamics/events/exit_call_event.py
appdynamics/events/tracer_events.py
appdynamics/exit_calls/__init__.py
appdynamics/exit_calls/backend_registry.py
appdynamics/exit_calls/exit_call.py
appdynamics/exit_calls/exit_call_service.py
appdynamics/exit_calls/exit_component.py
appdynamics/exit_calls/registered_backend_info.py
appdynamics/interceptor/__init__.py
appdynamics/interceptor/base.py
appdynamics/interceptor/boto/__init__.py
appdynamics/interceptor/boto/boto_interceptor.py
appdynamics/interceptor/boto/boto_resource_factory_interceptor.py
appdynamics/interceptor/boto/boto_service_interceptor.py
appdynamics/interceptor/boto/boto_service_interceptors/__init__.py
appdynamics/interceptor/boto/boto_service_interceptors/aws_lambda_interceptor.py
appdynamics/interceptor/boto/boto_utils/__init__.py
appdynamics/interceptor/boto/boto_utils/boto_backend_properties.py
appdynamics/interceptor/boto/boto_utils/boto_covered_methods.py
appdynamics/interceptor/boto/boto_utils/boto_header_interceptor.py
appdynamics/interceptor/http/__init__.py
appdynamics/interceptor/http/boto.py
appdynamics/interceptor/http/httplib.py
appdynamics/interceptor/http/requests.py
appdynamics/interceptor/http/tornado_httpclient.py
appdynamics/interceptor/http/urllib3.py
appdynamics/services/__init__.py
appdynamics/services/event_service.py
appdynamics/services/http_service.py
appdynamics/services/transaction_service.py
appdynamics_lambda_tracer-23.6.482.dist-info/LICENSE.txt
appdynamics_lambda_tracer-23.6.482.dist-info/METADATA
appdynamics_lambda_tracer-23.6.482.dist-info/WHEEL
appdynamics_lambda_tracer-23.6.482.dist-info/top_level.txt
appdynamics_lambda_tracer-23.6.482.dist-info/RECORD
