Metadata-Version: 2.1
Name: appdynamics-lambda-tracer
Version: 23.6.482
Summary: AppDynamics AWS Python Tracer
Home-page: UNKNOWN
Author: AppDynamics
License: LICENSE.txt
Platform: UNKNOWN
Requires-Python: >=3.7
Requires-Dist: httpx (==0.24.*)
Requires-Dist: contextvars ; python_version < "3.7"
